{
  "configVersion": 1,
  "timestamp": 1660780810800,
  "index": "/index.html",
  "assetGroups": [
    {
      "name": "app",
      "installMode": "prefetch",
      "updateMode": "prefetch",
      "cacheQueryOptions": {
        "ignoreVary": true
      },
      "urls": [
        "/1033.f13ca48a9b2cc63a.js",
        "/109.652087483f18b252.js",
        "/1118.1221324a654e9c88.js",
        "/1186.6b087d045dbcdd96.js",
        "/1217.1b4aea4ba010a68a.js",
        "/1536.5fdc09ccbd666679.js",
        "/1650.b6519bb722c59ff6.js",
        "/1709.ba895b3477366854.js",
        "/174.9f0d700d357af704.js",
        "/1835.1c4bf1163e4f9aa0.js",
        "/2073.cf70e3b5cf4a0386.js",
        "/2175.0140f07e60017908.js",
        "/2289.5133f41eb8fc3491.js",
        "/2349.45e177b37286b5c7.js",
        "/2698.68c89d7500d4f034.js",
        "/2773.9b576d38a22dd970.js",
        "/3074.59e81604bdb9a47b.js",
        "/3236.768d78ca3bbefab0.js",
        "/3262.25e10497ec7aabe2.js",
        "/3648.9a51e94caba97c3e.js",
        "/3804.eeeddaa4a58e3de6.js",
        "/388.43aaeccd0377cad7.js",
        "/4174.408f8c3e1419cd76.js",
        "/420.14dad33bb38957dc.js",
        "/4330.1c4a351b3c340176.js",
        "/4376.4c3ff8dca7c6a0c5.js",
        "/438.3fb919d4341312ea.js",
        "/4432.032a882a78cb212f.js",
        "/4651.4439712c7f583916.js",
        "/4711.0a5f73132d550c9e.js",
        "/4753.08d5927e465ff7da.js",
        "/4908.71bc54867e27ce41.js",
        "/4959.eab3a13286f3a7a8.js",
        "/5168.94201d2f877f711e.js",
        "/5349.92912c70dd35f965.js",
        "/5652.ac8941dc6819764a.js",
        "/5817.6c4db9fb0e6087ba.js",
        "/5836.d5054d991a405148.js",
        "/6120.abea0ba0c2a2e03a.js",
        "/6560.825889516e246b72.js",
        "/657.a4cd0e0c3ba23d6f.js",
        "/6666.ac2dd55e8b4ec2b2.js",
        "/7544.9a7dc870e2ad96ef.js",
        "/7602.f48cf27427470119.js",
        "/8136.5d6346304bb4c85e.js",
        "/8628.c8c23c1efc0b01f3.js",
        "/870.e086b9cbcafe79cc.js",
        "/8939.67364b80b4907507.js",
        "/9016.291926baac7c1003.js",
        "/9196.39c25e921eefe9dc.js",
        "/9230.d78e210bb9049531.js",
        "/9325.32f4d751c08933fc.js",
        "/9434.4c8827bb54ec2bde.js",
        "/9536.424bca4784e04c65.js",
        "/9654.5479ae0d369aac09.js",
        "/9824.c582ee190aea9312.js",
        "/9922.ac8636556410fd36.js",
        "/9958.bf72c775260753b6.js",
        "/common.179779f89e75b1bd.js",
        "/index.html",
        "/main.9c0360db2d70c177.js",
        "/manifest.webmanifest",
        "/polyfills-core-js.c8961a92c3ed4c69.js",
        "/polyfills-dom.5c5f23fb57b03028.js",
        "/polyfills.3ebd5e0cff18d293.js",
        "/runtime.066ddd81b72666b3.js",
        "/styles.a73c486ae5545c99.css"
      ],
      "patterns": []
    },
    {
      "name": "assets",
      "installMode": "lazy",
      "updateMode": "prefetch",
      "cacheQueryOptions": {
        "ignoreVary": true
      },
      "urls": [
        "/assets/Img_tab2/El gran negocio de las apps.jpg",
        "/assets/Img_tab2/Gasto en apps.png",
        "/assets/Img_tab2/Sensor tower.png",
        "/assets/Img_tab2/Worldwide-App-revenue.png",
        "/assets/Img_tab2/smartphone users.PNG",
        "/assets/Img_tab3/1.png",
        "/assets/Img_tab3/2.png",
        "/assets/Img_tab3/3.jpg",
        "/assets/Img_tab3/4.jpg",
        "/assets/icon/favicon.png",
        "/assets/icons/icon-128x128.png",
        "/assets/icons/icon-144x144.png",
        "/assets/icons/icon-152x152.png",
        "/assets/icons/icon-192x192.png",
        "/assets/icons/icon-384x384.png",
        "/assets/icons/icon-512x512.png",
        "/assets/icons/icon-72x72.png",
        "/assets/icons/icon-96x96.png",
        "/assets/shapes.svg"
      ],
      "patterns": []
    }
  ],
  "dataGroups": [],
  "hashTable": {
    "/1033.f13ca48a9b2cc63a.js": "ee8962e223a89f780bed08e16630e9c64b086174",
    "/109.652087483f18b252.js": "01fe5116355ec5b8cd7f5b443af05210cc55da57",
    "/1118.1221324a654e9c88.js": "5ca8530b3fb016e27f9d82c14cab646097b74fcf",
    "/1186.6b087d045dbcdd96.js": "93805c1a74874b3f18e2ad9fea6fc8ed692cbf96",
    "/1217.1b4aea4ba010a68a.js": "ae00ef1bf1fbaaba1dc22fca922088e3634dff57",
    "/1536.5fdc09ccbd666679.js": "2e9fda605eacb6c66ec4ed358d8138eb81498da5",
    "/1650.b6519bb722c59ff6.js": "037b724585807a71157e52e70b0da85a88be7cf3",
    "/1709.ba895b3477366854.js": "15d7e50ee05953c27a4c643cb507a2cfa2b1e76a",
    "/174.9f0d700d357af704.js": "d23394eacd5d32ee3e194582a0280832a27ebace",
    "/1835.1c4bf1163e4f9aa0.js": "f68732d090c506f6aed614fc320d73a6b4f4ddd8",
    "/2073.cf70e3b5cf4a0386.js": "4ad17028ad5e5910869c817ba0160a44faae75f4",
    "/2175.0140f07e60017908.js": "d8fb0dd12450f472dff328e0ff02f31924665000",
    "/2289.5133f41eb8fc3491.js": "58ece2fc28ee775183f7f19d1f4140958f9b3b1e",
    "/2349.45e177b37286b5c7.js": "25b8945de81f43b11ada7d4f6d7e0510a153104d",
    "/2698.68c89d7500d4f034.js": "8813a9f5144ffb733157b1730c3f3bf66d00a9b5",
    "/2773.9b576d38a22dd970.js": "1c2f1bca721815cb5f6d517d2f17d701b250e27c",
    "/3074.59e81604bdb9a47b.js": "0a4e8ac0881a46b27ea2a46d3bd8390883a3838f",
    "/3236.768d78ca3bbefab0.js": "c3876cba26560e9dd745d39ce7cd282917bfb555",
    "/3262.25e10497ec7aabe2.js": "cb4d3c78d530913417ea3be448cc54f85adf6c13",
    "/3648.9a51e94caba97c3e.js": "ea242df711820bf9c4e09c04afc5f5803e25b6f2",
    "/3804.eeeddaa4a58e3de6.js": "9143405901046ab15c837f62cf5645a6d69b787e",
    "/388.43aaeccd0377cad7.js": "8fad79fcefe4c534bc1d54ce71c043f04e267918",
    "/4174.408f8c3e1419cd76.js": "5360345b1fed267720a63f07dcf7731525a51172",
    "/420.14dad33bb38957dc.js": "b49a006caba131a259400c874ec6c056c819ca5d",
    "/4330.1c4a351b3c340176.js": "87da7445bb15808a34aff2186d7fc8cbece8fede",
    "/4376.4c3ff8dca7c6a0c5.js": "51ff3fc7e5e02f0eb6b2dd52d1cadae6973c9bff",
    "/438.3fb919d4341312ea.js": "1e98e7c436dfe43013fc217d9000c1e81ebfc3a1",
    "/4432.032a882a78cb212f.js": "ab7c7f4dbbff3ff1359f1a832fe44571a5ccb28c",
    "/4651.4439712c7f583916.js": "842ee1bfeebde46c0d15835b230f13df77d08563",
    "/4711.0a5f73132d550c9e.js": "4698b898ae53bf91832f626b1e5a05d49fe97378",
    "/4753.08d5927e465ff7da.js": "bb33d7272f87a3a0380a821b767fb0a6c3f2bd92",
    "/4908.71bc54867e27ce41.js": "f1ef87364be8a4df2bc1999664f783f8fa3cf31e",
    "/4959.eab3a13286f3a7a8.js": "23f107c8cecb88c5f67957eacc50d06cccd29a2f",
    "/5168.94201d2f877f711e.js": "151d7750e8527e2d1c765f03517c68e575f66af9",
    "/5349.92912c70dd35f965.js": "d0a89bf3c4010c9cce08d476c4715eee71a36d3c",
    "/5652.ac8941dc6819764a.js": "4fda199a059c01b1e3c9c6ca230f61a3e31a55dc",
    "/5817.6c4db9fb0e6087ba.js": "216c60905abe350489cf44967fec72cdaeafffa1",
    "/5836.d5054d991a405148.js": "d9ca36d2df28872d5d214deed8ba3e1b2661a22d",
    "/6120.abea0ba0c2a2e03a.js": "5be3e6e88f3ac89698136c5b7cf54ffa90fcaccd",
    "/6560.825889516e246b72.js": "fea3a6378259e067bc03d05f60516af5787d9048",
    "/657.a4cd0e0c3ba23d6f.js": "ded28d230b71f80ad71638033f3afafc44e8bbf2",
    "/6666.ac2dd55e8b4ec2b2.js": "52a23aa4d0e6b1b7955bc4d427beaca21717802a",
    "/7544.9a7dc870e2ad96ef.js": "162b0f211c7b74bfe0f4af22bcc4e4632770a7ed",
    "/7602.f48cf27427470119.js": "45346c282c87981f0ef212dc6a7226ef4f360fe4",
    "/8136.5d6346304bb4c85e.js": "a7ce76046000c0bb9e20ae5d71b959302da2c7b1",
    "/8628.c8c23c1efc0b01f3.js": "0c0f9466429677efb7cd55b4fc2ecbfd69817172",
    "/870.e086b9cbcafe79cc.js": "c9a4fc14f3de1c0b9aa4208976334756b51272d1",
    "/8939.67364b80b4907507.js": "7cfea73bdf56d53a8af2e16f2cadc2059a449ddf",
    "/9016.291926baac7c1003.js": "8bc2a96de37f7b19a595f401ddfbf2c8ea2873f2",
    "/9196.39c25e921eefe9dc.js": "55c36689b5beafe8099912483137c8fc63d11282",
    "/9230.d78e210bb9049531.js": "7d87d660f81774dd61909d4d31f8edfb41ed69a9",
    "/9325.32f4d751c08933fc.js": "b6675122e217a5aea4dc8427f393e1b691a9568c",
    "/9434.4c8827bb54ec2bde.js": "497709ab089f2b589ed16efab31f02fe2223735b",
    "/9536.424bca4784e04c65.js": "0592aeeadf9148e6a9c429dab7f6a74879407b8c",
    "/9654.5479ae0d369aac09.js": "4822bda04cf572cb0f83211c54530b04e32b63c8",
    "/9824.c582ee190aea9312.js": "0cee5cee4f2bdbbd61e3691407587cd145ba9aa4",
    "/9922.ac8636556410fd36.js": "c7b751fac10e86239478982abcb907d72f9870ff",
    "/9958.bf72c775260753b6.js": "73eab429438cc0c7d4e45c57f129afa01086551b",
    "/assets/Img_tab2/El gran negocio de las apps.jpg": "e135ab8bf73911e780c2ff4609ef26f9e77236e0",
    "/assets/Img_tab2/Gasto en apps.png": "4bf10fd180d0c58ad5e8887285e87332d44e926e",
    "/assets/Img_tab2/Sensor tower.png": "3fcd68fd5da88ca82238229948874b3c320a42ba",
    "/assets/Img_tab2/Worldwide-App-revenue.png": "bc9e8fa7e18d68f744e59033000630753fcfa6bc",
    "/assets/Img_tab2/smartphone users.PNG": "b8106ffe09d9f22f48aaf5587b88c7d83524f30d",
    "/assets/Img_tab3/1.png": "0de04ea37c1e2820928b8e2dcf6ffba5b555fe31",
    "/assets/Img_tab3/2.png": "cfd0c3b0df40509af3a0df8234bd3c0546c8a150",
    "/assets/Img_tab3/3.jpg": "24c7fa6eae2db16147c0dc2b180320ee1e07b884",
    "/assets/Img_tab3/4.jpg": "3b99bac3dfecfc651a34f1ecd68548f286cdf25a",
    "/assets/icon/favicon.png": "7798b8e0eb61d7375c245af78bbf5c916932bf13",
    "/assets/icons/icon-128x128.png": "dae3b6ed49bdaf4327b92531d4b5b4a5d30c7532",
    "/assets/icons/icon-144x144.png": "b0bd89982e08f9bd2b642928f5391915b74799a7",
    "/assets/icons/icon-152x152.png": "7479a9477815dfd9668d60f8b3b2fba709b91310",
    "/assets/icons/icon-192x192.png": "1abd80d431a237a853ce38147d8c63752f10933b",
    "/assets/icons/icon-384x384.png": "329749cd6393768d3131ed6304c136b1ca05f2fd",
    "/assets/icons/icon-512x512.png": "559d9c4318b45a1f2b10596bbb4c960fe521dbcc",
    "/assets/icons/icon-72x72.png": "c457e56089a36952cd67156f9996bc4ce54a5ed9",
    "/assets/icons/icon-96x96.png": "3914125a4b445bf111c5627875fc190f560daa41",
    "/assets/shapes.svg": "638f87e27e6fc7ddfd6e6b262ea70d690f6c7011",
    "/common.179779f89e75b1bd.js": "e2227e1ad88bd42fff5db3692ef7980af2d1c53c",
    "/index.html": "24c9d0b6f70b6b041906d65a1659eef914be709b",
    "/main.9c0360db2d70c177.js": "7534e970bec0759011352681d079c9c7ca56cf5e",
    "/manifest.webmanifest": "9a088b7c4339228d1082e666ce105dc889bc180c",
    "/polyfills-core-js.c8961a92c3ed4c69.js": "e44d42a08762418090a95d81b35288ab338d21e8",
    "/polyfills-dom.5c5f23fb57b03028.js": "06f5dc30f55bf9a3d9c6f9bca07c0041a6bbdaa0",
    "/polyfills.3ebd5e0cff18d293.js": "a4f03ad9599028ce006f4ac1ee55c63d4370a70b",
    "/runtime.066ddd81b72666b3.js": "210c56fd2f9e957a0d717b13c3ab1df66f56c8d0",
    "/styles.a73c486ae5545c99.css": "e5cb9996df8651cf224087dd26631775a7482a05"
  },
  "navigationUrls": [
    {
      "positive": true,
      "regex": "^\\/.*$"
    },
    {
      "positive": false,
      "regex": "^\\/(?:.+\\/)?[^/]*\\.[^/]*$"
    },
    {
      "positive": false,
      "regex": "^\\/(?:.+\\/)?[^/]*__[^/]*$"
    },
    {
      "positive": false,
      "regex": "^\\/(?:.+\\/)?[^/]*__[^/]*\\/.*$"
    }
  ],
  "navigationRequestStrategy": "performance"
}